{
    "format_version": "1.10.0",
    "minecraft:client_entity": {
        "description": {
            "identifier": "增幅法阵:幻戟",
            "materials": {
                "default": "entity_alphatest"
            },
            "textures": {
                "Map": "textures/entity/girl/战斗武器"
            },
            "geometry": {
                "default": "geometry.ocean_harpoon"
            },
            "scripts": {
                "animate": [
                    "watch"
                ]
            },
            "animations": {
                "watch": "controller.animation.ControlAttack.5",
                "attack": "animation.ocean_harpoon.loop",
                "basic": "animation.ocean_harpoon.start"
            },
            "render_controllers": [
                "controller.render.Map:X01"
            ],
            "spawn_egg": {
                "texture": "明镜阁_图标",
                "texture_index": 1
            }
        }
    }
}