{
    "format_version": "1.13.0",
    "minecraft:feature_rules": {
        "description": {
            "identifier": "结构规则:若水渊鲸塔",
            "places_feature": "结构定义:若水渊鲸塔"
        },
        "conditions": {
            "placement_pass": "underground_pass",
            "minecraft:biome_filter": [
                {
                    "any_of": [
                        {
                            "test": "has_biome_tag",
                            "operator": "==",
                            "value": "ocean"
                        },
                        {
                            "test": "has_biome_tag",
                            "operator": "==",
                            "value": "frozen_ocean"
                        },
                        {
                            "test": "has_biome_tag",
                            "operator": "==",
                            "value": "deep_ocean"
                        },
                        {
                            "test": "has_biome_tag",
                            "operator": "==",
                            "value": "warm_ocean"
                        },
                        {
                            "test": "has_biome_tag",
                            "operator": "==",
                            "value": "lukewarm_ocean"
                        },
                        {
                            "test": "has_biome_tag",
                            "operator": "==",
                            "value": "cold_ocean"
                        },
                        {
                            "test": "has_biome_tag",
                            "operator": "==",
                            "value": "deep_lukewarm_ocean"
                        },
                        {
                            "test": "has_biome_tag",
                            "operator": "==",
                            "value": "deep_cold_ocean"
                        },
                        {
                            "test": "has_biome_tag",
                            "operator": "==",
                            "value": "deep_frozen_ocean"
                        }
                    ]
                }
            ]
        },
        "distribution": {
            "iterations": 1,
            "x": {
                "distribution": "gaussian",
                "extent": [
                    0,
                    16
                ]
            },
            "y": {
                "distribution": "gaussian",
                "extent": [
                    32,
                    64
                ]
            },
            "z": {
                "distribution": "gaussian",
                "extent": [
                    0,
                    16
                ]
            }
        }
    }
}