{
    "format_version": "1.19.50",
    "minecraft:block": {
        "description": {
            "identifier": "输送链带:基础运输",
            "properties": {
                "Table:switch": [
                    0,
                    1,
                    2
                ],
                "Table:angle": [
                    2,
                    3,
                    4,
                    5
                ]
            }
        },
        "components": {
            "minecraft:geometry": "geometry.conveyor_belt.basic",
            "minecraft:display_name": "§6< §9输送链带§r _ §l§e基础运输§6 >§r",
            "minecraft:destructible_by_explosion": false,
            "minecraft:light_dampening": 0,
            "minecraft:breathability": "air",
            "minecraft:light_emission": 5,
            "minecraft:destructible_by_mining": {
                "seconds_to_destroy": 1.0
            },
            "minecraft:friction": 0.5,
            "minecraft:material_instances": {
                "*": {
                    "texture": "基础输送带",
                    "render_method": "alpha_test"
                }
            },
            "minecraft:collision_box": {
                "origin": [
                    -6,
                    0,
                    -8
                ],
                "size": [
                    12,
                    2,
                    16
                ]
            },
            "minecraft:selection_box": {
                "origin": [
                    -6,
                    0,
                    -8
                ],
                "size": [
                    12,
                    2,
                    16
                ]
            },
            "minecraft:on_player_placing": {
                "event": "放置方块"
            },
            "tag:conveyor_belt": {}
        },
        "permutations": [
            {
                "condition": "query.block_property('Table:switch') == 0",
                "components": {
                    "minecraft:queued_ticking": {
                        "looping": true,
                        "interval_range": [
                            5,
                            5
                        ],
                        "on_tick": {
                            "event": "状态侦测",
                            "target": "self"
                        }
                    }
                }
            },
            {
                "condition": "query.block_property('Table:switch') == 1",
                "components": {
                    "minecraft:queued_ticking": {
                        "looping": true,
                        "interval_range": [
                            5,
                            5
                        ],
                        "on_tick": {
                            "event": "执行功能",
                            "target": "self"
                        }
                    }
                }
            },
            {
                "condition": "query.block_property('Table:switch') == 2",
                "components": {
                    "minecraft:queued_ticking": {
                        "looping": true,
                        "interval_range": [
                            5,
                            5
                        ],
                        "on_tick": {
                            "event": "冷却完成",
                            "target": "self"
                        }
                    },
                    "tag:conveyor_belt.activation": {}
                }
            },
            {
                "condition": "query.block_property('Table:angle') == 2",
                "components": {
                    "minecraft:rotation": [
                        0,
                        0,
                        0
                    ],
                    "tag:conveyor_belt.face_load_Z": {}
                }
            },
            {
                "condition": "query.block_property('Table:angle') == 3",
                "components": {
                    "minecraft:rotation": [
                        0,
                        180,
                        0
                    ],
                    "tag:conveyor_belt.face_just_Z": {}
                }
            },
            {
                "condition": "query.block_property('Table:angle') == 4",
                "components": {
                    "minecraft:rotation": [
                        0,
                        90,
                        0
                    ],
                    "tag:conveyor_belt.face_load_X": {}
                }
            },
            {
                "condition": "query.block_property('Table:angle') == 5",
                "components": {
                    "minecraft:rotation": [
                        0,
                        270,
                        0
                    ],
                    "tag:conveyor_belt.face_just_X": {}
                }
            }
        ],
        "events": {
            "放置方块": {
                "set_block_property": {
                    "Table:angle": "(query.cardinal_facing_2d)"
                }
            },
            "状态侦测": {
                "sequence": [
                    {
                        "condition": "query.block_property('Table:angle') == 2 && query.block_neighbor_has_all_tags(0,0,1,'conveyor_belt.activation') == 1",
                        "set_block_property": {
                            "Table:switch": 1
                        }
                    },
                    {
                        "condition": "query.block_property('Table:angle') == 3 && query.block_neighbor_has_all_tags(0,0,-1,'conveyor_belt.activation') == 1",
                        "set_block_property": {
                            "Table:switch": 1
                        }
                    },
                    {
                        "condition": "query.block_property('Table:angle') == 4 && query.block_neighbor_has_all_tags(1,0,0,'conveyor_belt.activation') == 1",
                        "set_block_property": {
                            "Table:switch": 1
                        }
                    },
                    {
                        "condition": "query.block_property('Table:angle') == 5 && query.block_neighbor_has_all_tags(-1,0,0,'conveyor_belt.activation') == 1",
                        "set_block_property": {
                            "Table:switch": 1
                        }
                    }
                ]
            },
            "执行功能": {
                "sequence": [
                    //传送带的运行方向为: 朝 北 运输
                    {
                        "condition": "query.block_property('Table:angle') == 2",
                        "sequence": [
                            {
                                "condition": "query.block_neighbor_has_all_tags(0,0,-1,'conveyor_belt.face_load_Z') == 1",
                                "run_command": {
                                    "command": [
                                        "execute as @e [type=item,dy=1] run tp @s ~ ~ ~-1"
                                    ]
                                }
                            },
                            {
                                "condition": "query.block_neighbor_has_all_tags(0,0,-1,'conveyor_belt_transfer') == 1",
                                "run_command": {
                                    "command": [
                                        "execute as @e [type=item,dy=1] run tp @s ~ ~ ~-1"
                                    ]
                                }
                            }
                        ]
                    },
                    //传送带的运行方向为: 朝 南 运输
                    {
                        "condition": "query.block_property('Table:angle') == 3",
                        "sequence": [
                            {
                                "condition": "query.block_neighbor_has_all_tags(0,0,1,'conveyor_belt.face_just_Z') == 1",
                                "run_command": {
                                    "command": [
                                        "execute as @e [type=item,dy=1] run tp @s ~ ~ ~1"
                                    ]
                                }
                            },
                            {
                                "condition": "query.block_neighbor_has_all_tags(0,0,1,'conveyor_belt_transfer') == 1",
                                "run_command": {
                                    "command": [
                                        "execute as @e [type=item,dy=1] run tp @s ~ ~ ~1"
                                    ]
                                }
                            }
                        ]
                    },
                    //传送带的运行方向为: 朝 西 运输
                    {
                        "condition": "query.block_property('Table:angle') == 4",
                        "sequence": [
                            {
                                "condition": "query.block_neighbor_has_all_tags(-1,0,0,'conveyor_belt.face_load_X') == 1",
                                "run_command": {
                                    "command": [
                                        "execute as @e [type=item,dy=1] run tp @s ~-1 ~ ~"
                                    ]
                                }
                            },
                            {
                                "condition": "query.block_neighbor_has_all_tags(-1,0,0,'conveyor_belt_transfer') == 1",
                                "run_command": {
                                    "command": [
                                        "execute as @e [type=item,dy=1] run tp @s ~-1 ~ ~"
                                    ]
                                }
                            }
                        ]
                    },
                    //传送带的运行方向为: 朝 东 运输
                    {
                        "condition": "query.block_property('Table:angle') == 5",
                        "sequence": [
                            {
                                "condition": "query.block_neighbor_has_all_tags(1,0,0,'conveyor_belt.face_just_X') == 1",
                                "run_command": {
                                    "command": [
                                        "execute as @e [type=item,dy=1] run tp @s ~1 ~ ~"
                                    ]
                                }
                            },
                            {
                                "condition": "query.block_neighbor_has_all_tags(1,0,0,'conveyor_belt_transfer') == 1",
                                "run_command": {
                                    "command": [
                                        "execute as @e [type=item,dy=1] run tp @s ~1 ~ ~"
                                    ]
                                }
                            }
                        ]
                    },
                    {
                        "set_block_property": {
                            "Table:switch": 2
                        }
                    }
                ]
            },
            "冷却完成": {
                "set_block_property": {
                    "Table:switch": 0
                }
            }
        }
    }
}