{
    "format_version": "1.8.5",
    "minecraft:recipe_shaped": {
        "description": {
            "identifier": "addons.item.basic_original"
        },
        "tags": [
            "crafting_table"
        ],
        "pattern": [
            "0*0",
            "*X*",
            "0*0"
        ],
        "key": {
            "*": {
                "item": "合金材料:特种合金"
            },
            "0": {
                "item": "合金材料:钢岩合金"
            },
            "X": {
                "item": "quartz"
            }
        },
        "result": {
            "item": "特制模板:空灵单元"
        }
    }
}