{
    "format_version": "1.16.100",
    "minecraft:item": {
        "description": {
            "identifier": "魔法卷轴:逆影疾行",
            "category": "equipment"
        },
        "components": {
            "minecraft:can_destroy_in_creative": false,
            "minecraft:allow_off_hand": false,
            "minecraft:hand_equipped": true,
            "minecraft:max_stack_size": 1,
            "minecraft:foil": true,
            "minecraft:damage": 1,
            "minecraft:icon": {
                "texture": "魔法卷轴"
            },
            "minecraft:display_name": {
                "value": "§6《 逆影疾行 》§r"
            },
            "minecraft:creative_category": {
                "parent": "equipment"
            },
            "minecraft:on_use": {
                "on_use": {
                    "event": "阅读书籍",
                    "target": "self"
                }
            },
            "minecraft:cooldown": {
                "category": "逆影疾行",
                "duration": 15
            },
            "minecraft:render_offsets": {
                "main_hand": {
                    "third_person": {
                        "position": [
                            0.05,
                            0.65,
                            -0.3
                        ],
                        "scale": [
                            0.05,
                            0.05,
                            0.05
                        ]
                    },
                    "first_person": {
                        "position": [
                            1.5,
                            -0.5,
                            -3.0
                        ],
                        "scale": [
                            0.09,
                            0.09,
                            0.09
                        ]
                    }
                }
            },
            "minecraft:durability": {
                "max_durability": 350,
                "damage_chance": {
                    "min": 0,
                    "max": 0
                }
            }
        },
        "events": {
            "阅读书籍": {
                "sequence": [
                    {
                        "run_command": {
                            "command": [
                                "effect @s invisibility 15 00 true",
                                "effect @s night_vision 15 00 true",
                                "effect @s jump_boost   15 09 true",
                                "effect @s slowness 35 01 true",
                                "effect @s speed    15 31 true"
                            ]
                        }
                    },
                    {
                        "damage": {
                            "type": "magic",
                            "amount": 400
                        }
                    }
                ]
            }
        }
    }
}